probs/__init__.py
probs/counting.py
probs/floats.py
probs/operations.py
probs/py.typed
probs/rv.py
probs/continuous/__init__.py
probs/continuous/beta.py
probs/continuous/exponential.py
probs/continuous/gamma.py
probs/continuous/inv_gamma.py
probs/continuous/laplace.py
probs/continuous/lomax.py
probs/continuous/normal.py
probs/continuous/rv.py
probs/continuous/students_t.py
probs/continuous/uniform.py
probs/discrete/__init__.py
probs/discrete/bernoulli.py
probs/discrete/beta_binomial.py
probs/discrete/binomial.py
probs/discrete/dice_roll.py
probs/discrete/geometric.py
probs/discrete/negative_binomial.py
probs/discrete/poisson.py
probs/discrete/rv.py
tests/__init__.py
tests/floats_test.py
tests/rv_test.py
tests/continuous/__init__.py
tests/continuous/normal_test.py
tests/continuous/uniform_test.py
tests/discrete/__init__.py
tests/discrete/binomial_test.py
tests/discrete/dice_roll_test.py
tests/discrete/rv_test.py
probs-0.0.6.dist-info/LICENSE
probs-0.0.6.dist-info/METADATA
probs-0.0.6.dist-info/WHEEL
probs-0.0.6.dist-info/top_level.txt
probs-0.0.6.dist-info/RECORD
